dhybridrpy/__init__.py
dhybridrpy/containers.py
dhybridrpy/data.py
dhybridrpy/dhybridrpy.py
dhybridrpy_test-2.dist-info/LICENSE
dhybridrpy_test-2.dist-info/METADATA
dhybridrpy_test-2.dist-info/WHEEL
dhybridrpy_test-2.dist-info/top_level.txt
dhybridrpy_test-2.dist-info/RECORD
