Metadata-Version: 2.2
Name: dhybridrpy-test
Version: 2
Summary: A Python package to easily read input + output data from dHybridR.
Home-page: https://github.com/bwostler/dhybridrpy
Author: Bricker Ostler, Miha Cernetic
Author-email: bostler@uchicago.edu
Requires-Python: >=3.8
License-File: LICENSE
Requires-Dist: h5py
Requires-Dist: matplotlib
Requires-Dist: numpy
Requires-Dist: ruff
Requires-Dist: h5py
Requires-Dist: f90nml
Requires-Dist: pre-commit
Requires-Dist: dask
Dynamic: author
Dynamic: author-email
Dynamic: home-page
